dynamite_nsm/__init__.py
dynamite_nsm/const.py
dynamite_nsm/exceptions.py
dynamite_nsm/logger.py
dynamite_nsm/package_manager.py
dynamite_nsm/utilities.py
dynamite_nsm/bin/bpf_validate
dynamite_nsm/cmd/__init__.py
dynamite_nsm/cmd/base_interface.py
dynamite_nsm/cmd/config_object_interfaces.py
dynamite_nsm/cmd/inspection_helpers.py
dynamite_nsm/cmd/interface_operations.py
dynamite_nsm/cmd/service_interfaces.py
dynamite_nsm/cmd/agent/__init__.py
dynamite_nsm/cmd/agent/__main__.py
dynamite_nsm/cmd/agent/install/__init__.py
dynamite_nsm/cmd/agent/install/__main__.py
dynamite_nsm/cmd/agent/optimize/__init__.py
dynamite_nsm/cmd/agent/optimize/__main__.py
dynamite_nsm/cmd/agent/process/__init__.py
dynamite_nsm/cmd/agent/process/__main__.py
dynamite_nsm/cmd/agent/uninstall/__init__.py
dynamite_nsm/cmd/agent/uninstall/__main__.py
dynamite_nsm/cmd/auth/__init__.py
dynamite_nsm/cmd/auth/__main__.py
dynamite_nsm/cmd/auth/install/__init__.py
dynamite_nsm/cmd/auth/install/__main__.py
dynamite_nsm/cmd/auth/uninstall/__init__.py
dynamite_nsm/cmd/auth/uninstall/__main__.py
dynamite_nsm/cmd/elasticsearch/__init__.py
dynamite_nsm/cmd/elasticsearch/__main__.py
dynamite_nsm/cmd/elasticsearch/config/__init__.py
dynamite_nsm/cmd/elasticsearch/config/__main__.py
dynamite_nsm/cmd/elasticsearch/config/java/__init__.py
dynamite_nsm/cmd/elasticsearch/config/java/__main__.py
dynamite_nsm/cmd/elasticsearch/config/main/__init__.py
dynamite_nsm/cmd/elasticsearch/config/main/__main__.py
dynamite_nsm/cmd/elasticsearch/config/users/__init__.py
dynamite_nsm/cmd/elasticsearch/config/users/__main__.py
dynamite_nsm/cmd/elasticsearch/install/__init__.py
dynamite_nsm/cmd/elasticsearch/install/__main__.py
dynamite_nsm/cmd/elasticsearch/process/__init__.py
dynamite_nsm/cmd/elasticsearch/process/__main__.py
dynamite_nsm/cmd/elasticsearch/uninstall/__init__.py
dynamite_nsm/cmd/elasticsearch/uninstall/__main__.py
dynamite_nsm/cmd/filebeat/__init__.py
dynamite_nsm/cmd/filebeat/__main__.py
dynamite_nsm-1.1.4.dist-info/LICENSE.txt
dynamite_nsm-1.1.4.dist-info/METADATA
dynamite_nsm-1.1.4.dist-info/WHEEL
dynamite_nsm-1.1.4.dist-info/top_level.txt
dynamite_nsm-1.1.4.dist-info/RECORD
