Metadata-Version: 2.1
Name: dynamite-nsm
Version: 1.1.4
Summary: DynamiteNSM is a lightweight, versatile network security monitor designed to make securing your network environment simple and intuitive.
Home-page: https://github.com/DynamiteAI/dynamite-nsm
Author: Dynamite Analytics
Author-email: admin@dynamite.ai
License: GPL 3
Platform: UNKNOWN
Classifier: Development Status :: 4 - Beta
Classifier: Natural Language :: English
Classifier: Programming Language :: Python :: 3.7
Classifier: Operating System :: POSIX :: Linux
Classifier: Environment :: Console
Classifier: Topic :: System :: Networking :: Monitoring
Classifier: Topic :: Security
Classifier: License :: OSI Approved :: GNU General Public License (GPL)
Requires-Python: >=3.7.0
Requires-Dist: bcrypt (==3.2.0)
Requires-Dist: coloredlogs (==15.0)
Requires-Dist: progressbar (==2.5)
Requires-Dist: tabulate (==0.8.9)
Requires-Dist: PyYAML (==6.0)
Requires-Dist: psutil (==5.8.0)
Requires-Dist: docstring-parser (==0.7.3)
Requires-Dist: marshmallow (==3.11.1)
Requires-Dist: pytest (==6.2.2)
Requires-Dist: python-crontab (==2.5.1)
Requires-Dist: python-daemon (==2.3.0)
Requires-Dist: requests (==2.25.1)
Requires-Dist: SQLAlchemy (==1.4.7)
Requires-Dist: Unidecode (==1.2.0)
